meta_yt/__init__.py
meta_yt/caption.py
meta_yt/exceptions.py
meta_yt/langauge.py
meta_yt/query.py
meta_yt/srt.py
meta_yt/video.py
meta_yt/youtube.py
meta_yt-0.1.9.dist-info/LICENSE
meta_yt-0.1.9.dist-info/METADATA
meta_yt-0.1.9.dist-info/WHEEL
meta_yt-0.1.9.dist-info/top_level.txt
meta_yt-0.1.9.dist-info/RECORD
