Metadata-Version: 2.1
Name: meta-yt
Version: 0.1.9
Summary: A lightweight Python library for fetching YouTube videos' metadata.
Home-page: https://github.com/Rystal-Team/Meta-YT
Author: Rystal-Team
Author-email: code@rystal.xyz
License: MIT
Classifier: License :: OSI Approved :: MIT License
Classifier: Programming Language :: Python :: 3
Classifier: Programming Language :: Python :: 3.7
Classifier: Programming Language :: Python :: 3.8
Classifier: Programming Language :: Python :: 3.9
Classifier: Operating System :: OS Independent
Requires-Python: >=3.7
License-File: LICENSE
Requires-Dist: requests
Requires-Dist: xmltodict
